AYAN/src/Petspackage_Ayan_123/MYDEARPET.py
AYAN/src/Petspackage_Ayan_123/__init__.py
Petspackage_Ayan_123-0.0.1.dist-info/LICENSE
Petspackage_Ayan_123-0.0.1.dist-info/METADATA
Petspackage_Ayan_123-0.0.1.dist-info/WHEEL
Petspackage_Ayan_123-0.0.1.dist-info/top_level.txt
Petspackage_Ayan_123-0.0.1.dist-info/RECORD
