Metadata-Version: 2.1
Name: Petspackage_Ayan_123
Version: 0.0.1
Summary: It helps the user to classify according to their breeds and types
Author-email: Ayan <ayan.mukherjee2022@vitstudent.ac.in>
Classifier: Programming Language :: Python :: 3
Classifier: License :: OSI Approved :: MIT License
Classifier: Operating System :: OS Independent
Requires-Python: >=3.7
License-File: LICENSE
